ConsoleType/__init__.py
ConsoleType/_login.py
consoletype-1.4.5.dist-info/licenses/LICENSE
consoletype-1.4.5.dist-info/METADATA
consoletype-1.4.5.dist-info/WHEEL
consoletype-1.4.5.dist-info/top_level.txt
consoletype-1.4.5.dist-info/RECORD
