Metadata-Version: 2.4
Name: ConsoleType
Version: 1.4.5
Summary: My Project
Home-page: https://github.com/Vaddlkk/ConsoleType
Author: Vadim | Mur Studio
Author-email: somerare23@gmail.com
License: MIT
Classifier: Programming Language :: Python :: 3
Classifier: License :: OSI Approved :: MIT License
Classifier: Operating System :: OS Independent
Requires-Python: >=3.8, <3.15
License-File: LICENSE
Requires-Dist: requests>=2.0
Dynamic: author
Dynamic: author-email
Dynamic: classifier
Dynamic: description
Dynamic: description-content-type
Dynamic: home-page
Dynamic: license
Dynamic: license-file
Dynamic: requires-dist
Dynamic: requires-python
Dynamic: summary
